LICENSE
MANIFEST.in
README.md
setup.py
raster_proc/__init__.py
raster_proc.egg-info/PKG-INFO
raster_proc.egg-info/SOURCES.txt
raster_proc.egg-info/dependency_links.txt
raster_proc.egg-info/requires.txt
raster_proc.egg-info/top_level.txt
raster_proc/modeling/__init__.py
raster_proc/modeling/model.py
raster_proc/plotting/__init__.py
raster_proc/plotting/plot.py
raster_proc/processing/__init__.py
raster_proc/processing/process.py
raster_proc/timeseries/__init__.py
raster_proc/timeseries/ts.py
scripts/exploring_Sentinel2_STAC.py
venv/bin/gdal2tiles.py
venv/bin/gdal2xyz.py
venv/bin/gdal_calc.py
venv/bin/gdal_edit.py
venv/bin/gdal_fillnodata.py
venv/bin/gdal_merge.py
venv/bin/gdal_pansharpen.py
venv/bin/gdal_polygonize.py
venv/bin/gdal_proximity.py
venv/bin/gdal_retile.py
venv/bin/gdal_sieve.py
venv/bin/gdalattachpct.py
venv/bin/gdalcompare.py
venv/bin/gdalmove.py
venv/bin/ogrmerge.py
venv/bin/pct2rgb.py
venv/bin/rgb2pct.py