Metadata-Version: 2.1
Name: raster-proc
Version: 0.0.1
License-File: LICENSE
Requires-Dist: GDAL==3.4.3
Requires-Dist: numpy==1.26.2
Requires-Dist: fiona==1.9.5
Requires-Dist: shapely==2.0.2
Requires-Dist: contextily==1.4.0
Requires-Dist: geopandas==0.14.1
Requires-Dist: Cartopy==0.22.0
Requires-Dist: pyproj==3.6.1
Requires-Dist: matplotlib==3.8.2
Requires-Dist: seaborn==0.13.0
Requires-Dist: pandas==2.1.4
Requires-Dist: pathlib==1.0.1
Requires-Dist: DateTime==5.4
Requires-Dist: mapclassify
Requires-Dist: folium==0.15.1
Requires-Dist: rasterio==1.3.9
Requires-Dist: xarray==2023.12.0
Requires-Dist: rioxarray==0.15.0
Requires-Dist: earthpy==0.9.4
Requires-Dist: pystac==1.9.0
Requires-Dist: planetary-computer==1.0.0
Requires-Dist: pystac-client==0.7.5
